bthlabs_jsonrpc_aiohttp/__init__.py
bthlabs_jsonrpc_aiohttp/executor.py
bthlabs_jsonrpc_aiohttp/views.py
bthlabs_jsonrpc_aiohttp-1.0.0.dist-info/LICENSE
bthlabs_jsonrpc_aiohttp-1.0.0.dist-info/WHEEL
bthlabs_jsonrpc_aiohttp-1.0.0.dist-info/METADATA
bthlabs_jsonrpc_aiohttp-1.0.0.dist-info/RECORD
