Metadata-Version: 2.1
Name: bthlabs-jsonrpc-aiohttp
Version: 1.0.0
Summary: BTHLabs JSONRPC - aiohttp integration
Home-page: https://projects.bthlabs.pl/bthlabs-jsonrpc/
License: MIT
Author: Tomek Wójcik
Author-email: contact@bthlabs.pl
Maintainer: BTHLabs
Maintainer-email: contact@bthlabs.pl
Requires-Python: >=3.10,<4.0
Classifier: License :: OSI Approved :: MIT License
Classifier: Programming Language :: Python :: 3
Classifier: Programming Language :: Python :: 3.10
Requires-Dist: aiohttp (>=3.6,<4.0)
Requires-Dist: bthlabs-jsonrpc-core (==1.0.0)
Project-URL: Documentation, https://projects.bthlabs.pl/bthlabs-jsonrpc/aiohttp/
Project-URL: Repository, https://git.bthlabs.pl/tomekwojcik/bthlabs-jsonrpc/
